zest/pocompile/__init__.py
zest/pocompile/compile.py
zest.pocompile-2.0.0.dist-info/METADATA
zest.pocompile-2.0.0.dist-info/WHEEL
zest.pocompile-2.0.0.dist-info/entry_points.txt
zest.pocompile-2.0.0.dist-info/top_level.txt
zest.pocompile-2.0.0.dist-info/RECORD
