Metadata-Version: 2.1
Name: zest.pocompile
Version: 2.0.0
Summary: Compile po files when releasing a package
Home-page: https://github.com/zestsoftware/zest.pocompile
Author: Maurits van Rees
Author-email: m.van.rees@zestsoftware.nl
License: GPL
Keywords: i18n locales po compile release
Classifier: Development Status :: 5 - Production/Stable
Classifier: Framework :: Buildout
Classifier: License :: OSI Approved :: GNU General Public License (GPL)
Classifier: Programming Language :: Python
Classifier: Programming Language :: Python :: 3
Classifier: Programming Language :: Python :: 3.8
Classifier: Programming Language :: Python :: 3.9
Classifier: Programming Language :: Python :: 3.10
Classifier: Programming Language :: Python :: 3.11
Classifier: Topic :: Software Development :: Internationalization
Requires-Python: >=3.8
Requires-Dist: setuptools
Requires-Dist: python-gettext
